{
  "schema": 2,
  "generated_utc": "2026-05-17T13:01:22+00:00",
  "items": [
    {
      "id": "5d4bbf488e7f",
      "pillar": "sneakers",
      "title": "Nigel Sylvester x Air Jordan 4 “Brick After Brick” May Release Date & Info",
      "source": "NiceKicks",
      "source_url": "https://www.nicekicks.com/nigel-sylvester-air-jordan-4-brick-after-brick-iq8055-100-drop/",
      "thumbnail": "/drops/thumbs/5d4bbf488e7f.jpg",
      "published": "2026-05-13T07:21:30",
      "relative_time": "today",
      "score": 7.5,
      "release_badge": "🔥 Banger"
    },
    {
      "id": "43151d13faa3",
      "pillar": "sneakers",
      "title": "RUMORED: Air Jordan 8 PRM “BIN 23” Set for Summer 2026 Release",
      "source": "NiceKicks",
      "source_url": "https://www.nicekicks.com/air-jordan-8-prm-bin-23-io2053-300-drop/",
      "thumbnail": "/drops/thumbs/43151d13faa3.png",
      "published": "2026-05-12T11:21:07",
      "relative_time": "today",
      "score": 5.0,
      "release_badge": "🔥 Banger"
    },
    {
      "id": "37fc53e0f8e7",
      "pillar": "sneakers",
      "title": "The Air Jordan 3 “World’s Best Dad” Releases Tomorrow",
      "source": "JustFreshKicks",
      "source_url": "https://justfreshkicks.com/air-jordan-3-worlds-best-dad-if4396-103/",
      "thumbnail": "/drops/thumbs/37fc53e0f8e7.jpg",
      "published": "2026-05-15T04:32:00",
      "relative_time": "today",
      "score": 3.0,
      "release_badge": "Drops This Week"
    },
    {
      "id": "7d4dc371b041",
      "pillar": "sneakers",
      "title": "Air Jordan 1 High OG “Shop Jacket” (Workwear) Releases May 2026",
      "source": "Sneakerfiles",
      "source_url": "https://www.sneakerfiles.com/air-jordan-1-high-og-workwear/",
      "thumbnail": "/drops/thumbs/7d4dc371b041.jpg",
      "published": "2026-05-15T00:28:37",
      "relative_time": "today",
      "score": 3.0,
      "release_badge": "Drops This Month"
    },
    {
      "id": "f931c0c69400",
      "pillar": "sneakers",
      "title": "Air Jordan 1 High OG WMNS “Workwear” (FD2596-201) May Release Date & Info",
      "source": "NiceKicks",
      "source_url": "https://www.nicekicks.com/air-jordan-1-high-og-wmns-workwear-fd2596-201-drop/",
      "thumbnail": "/drops/thumbs/f931c0c69400.jpg",
      "published": "2026-05-10T15:44:38",
      "relative_time": "today",
      "score": 3.0,
      "release_badge": "Drops This Month"
    },
    {
      "id": "dd5fb84e4443",
      "pillar": "sneakers",
      "title": "Air Jordan 3 “Brazil” Releases May 16th",
      "source": "SneakerBarDetroit",
      "source_url": "https://sneakerbardetroit.com/air-jordan-3-brazil-iv4871-400-release-date/",
      "thumbnail": "/drops/thumbs/dd5fb84e4443.webp",
      "published": "",
      "relative_time": "today",
      "score": 3.0,
      "release_badge": "Drops This Month"
    },
    {
      "id": "d68700a4442e",
      "pillar": "sneakers",
      "title": "The Air Jordan 1 Low in “Phantom” & “Pine Green” Lands in June 2026",
      "source": "JustFreshKicks",
      "source_url": "https://justfreshkicks.com/air-jordan-1-low-phantom-green-ir2283-030/",
      "thumbnail": "/drops/thumbs/d68700a4442e.png",
      "published": "2026-05-14T13:12:48",
      "relative_time": "today",
      "score": 2.4,
      "release_badge": "Drops Next Month"
    },
    {
      "id": "ff9bcc240957",
      "pillar": "sneakers",
      "title": "Air Jordan 3 Golf “Black Cement” Releases February 2027",
      "source": "Sneakerfiles",
      "source_url": "https://www.sneakerfiles.com/air-jordan-3-golf-black-cement-2027/",
      "thumbnail": "/drops/thumbs/ff9bcc240957.jpg",
      "published": "2026-05-17T02:09:57",
      "relative_time": "today",
      "score": 2.0,
      "release_badge": ""
    },
    {
      "id": "fbcaff4991e8",
      "pillar": "hiphop",
      "title": "Leaders Demand Apology From Kevin Hart & Netflix Over George Floyd Joke & Note Donald Trump Double Standard",
      "source": "AllHipHop",
      "source_url": "https://allhiphop.com/news/leaders-demand-apology-from-kevin-hart-netflix-over-george-floyd-joke-note-donald-trump-double-standard/",
      "thumbnail": "/drops/thumbs/fbcaff4991e8.jpg",
      "published": "2026-05-17T09:00:40",
      "relative_time": "today",
      "score": 1.0,
      "release_badge": ""
    },
    {
      "id": "dea904ca506e",
      "pillar": "hiphop",
      "title": "‘I was overdue for a new bra’: Florida woman goes to Victoria’s Secret. Then she tries the new, viral T-shirt bra",
      "source": "AllHipHop",
      "source_url": "https://allhiphop.com/newsbreak/florida-victorias-secret-t-shit-bra/",
      "thumbnail": "/drops/thumbs/dea904ca506e.jpg",
      "published": "2026-05-17T09:00:00",
      "relative_time": "today",
      "score": 1.0,
      "release_badge": ""
    },
    {
      "id": "ec0f05bde3d7",
      "pillar": "hiphop",
      "title": "2K Foundations Unveils Refurbished Basketball Court in San Francisco",
      "source": "The Source",
      "source_url": "https://thesource.com/2026/05/17/2k-foundations-boys-and-girls-club-san-francisco-court/",
      "thumbnail": "/drops/thumbs/ec0f05bde3d7.jpg",
      "published": "2026-05-17T06:38:26",
      "relative_time": "today",
      "score": 1.0,
      "release_badge": ""
    },
    {
      "id": "f3fcd1ca22d9",
      "pillar": "hiphop",
      "title": "Netflix Sets Fall Premiere for ‘A Different World’ Sequel",
      "source": "The Source",
      "source_url": "https://thesource.com/2026/05/17/a-different-world-sequel-netflix-fall-premiere/",
      "thumbnail": "/drops/thumbs/f3fcd1ca22d9.jpg",
      "published": "2026-05-17T06:25:46",
      "relative_time": "today",
      "score": 1.0,
      "release_badge": ""
    },
    {
      "id": "b2fcbe879449",
      "pillar": "hiphop",
      "title": "Brett Ratner Joins Presidential Delegation to China for ‘Rush Hour 4’",
      "source": "The Source",
      "source_url": "https://thesource.com/2026/05/17/brett-ratner-rush-hour-4-china-visit-trump/",
      "thumbnail": "/drops/thumbs/b2fcbe879449.jpg",
      "published": "2026-05-17T06:15:00",
      "relative_time": "today",
      "score": 1.0,
      "release_badge": ""
    },
    {
      "id": "2b85aefd2524",
      "pillar": "hiphop",
      "title": "Nashville man looks at steak at Kroger—and opts for the cheapest possible: ‘We’ve all thought this.. he just did it’",
      "source": "AllHipHop",
      "source_url": "https://allhiphop.com/newsbreak/kroger-chuck-roast-vs-ribeye/",
      "thumbnail": "/drops/thumbs/2b85aefd2524.jpg",
      "published": "2026-05-17T06:00:00",
      "relative_time": "today",
      "score": 1.0,
      "release_badge": ""
    },
    {
      "id": "a83f75f42386",
      "pillar": "hiphop",
      "title": "Will Smith to Star in Amazon MGM Action Thriller ‘Supermax’",
      "source": "The Source",
      "source_url": "https://thesource.com/2026/05/17/will-smith-supermax-david-gordon-green-amazon-mgm/",
      "thumbnail": "/drops/thumbs/a83f75f42386.jpg",
      "published": "2026-05-17T05:54:00",
      "relative_time": "today",
      "score": 1.0,
      "release_badge": ""
    },
    {
      "id": "4ef7fdbd2ead",
      "pillar": "hiphop",
      "title": "21 Savage Hosts Financial Literacy Graduation for Atlanta Youth",
      "source": "The Source",
      "source_url": "https://thesource.com/2026/05/17/21-savage-hosts-financial-literacy-graduation-for-atlanta-youth/",
      "thumbnail": "/drops/thumbs/4ef7fdbd2ead.jpg",
      "published": "2026-05-17T05:47:00",
      "relative_time": "today",
      "score": 1.0,
      "release_badge": ""
    },
    {
      "id": "254a561ec862",
      "pillar": "anime",
      "title": "Shangri-La Frontier Is Still The Best Anime To Watch After Solo Leveling",
      "source": "ScreenRant/Anime",
      "source_url": "https://screenrant.com/shangri-la-frontier-best-anime-watch-after-solo-leveling/",
      "thumbnail": "/drops/thumbs/254a561ec862.jpg",
      "published": "",
      "relative_time": "today",
      "score": 1.0,
      "release_badge": ""
    },
    {
      "id": "17c4bd69062e",
      "pillar": "anime",
      "title": "Demon Slayer: Infinity Castle Part 2 Is Finally Going To Give The Most Controversial Hashira His Time To Shine",
      "source": "ScreenRant/Anime",
      "source_url": "https://screenrant.com/demon-slayer-sanemi-most-controversial-hashira-explained/",
      "thumbnail": "/drops/thumbs/17c4bd69062e.jpg",
      "published": "",
      "relative_time": "today",
      "score": 1.0,
      "release_badge": ""
    },
    {
      "id": "832fd512ad43",
      "pillar": "anime",
      "title": "To understand My Hero Academia you really have to watch its perfect spinoff",
      "source": "Polygon/Anime",
      "source_url": "https://www.polygon.com/my-hero-academia-vigilantes-mha-perfect-spinoff/",
      "thumbnail": "/drops/thumbs/832fd512ad43.jpg",
      "published": "",
      "relative_time": "today",
      "score": 1.0,
      "release_badge": ""
    },
    {
      "id": "9665f2a815bf",
      "pillar": "anime",
      "title": "Boruto can never be the next Naruto, and that's OK",
      "source": "Polygon/Anime",
      "source_url": "https://www.polygon.com/boruto-naruto-sequel-10-year-anniversary-flawed-legacy/",
      "thumbnail": "/drops/thumbs/9665f2a815bf.png",
      "published": "",
      "relative_time": "today",
      "score": 1.0,
      "release_badge": ""
    },
    {
      "id": "f7c823e88274",
      "pillar": "anime",
      "title": "Black Clover Filler List: Every Episode You Can Skip",
      "source": "ScreenRant/Anime",
      "source_url": "https://screenrant.com/every-black-clover-filler-episode/",
      "thumbnail": "/drops/thumbs/f7c823e88274.png",
      "published": "",
      "relative_time": "today",
      "score": 1.0,
      "release_badge": ""
    },
    {
      "id": "f23569725308",
      "pillar": "anime",
      "title": "Hunter x Hunter Filler List: Every Episode Fans Can Skip",
      "source": "ScreenRant/Anime",
      "source_url": "https://screenrant.com/hunter-x-hunter-filler-list-every-episode-skip/",
      "thumbnail": "/drops/thumbs/f23569725308.png",
      "published": "",
      "relative_time": "today",
      "score": 1.0,
      "release_badge": ""
    },
    {
      "id": "e4764ade8fec",
      "pillar": "anime",
      "title": "I Became a Legend After My 10 Year-Long Last Stand Anime Reveals Ending Theme Song Artist",
      "source": "AnimeNewsNetwork",
      "source_url": "https://www.animenewsnetwork.com/news/2026-05-17/i-became-a-legend-after-my-10-year-long-last-stand-anime-reveals-ending-theme-song-artist/.237442",
      "thumbnail": "/drops/thumbs/e4764ade8fec.jpg",
      "published": "",
      "relative_time": "today",
      "score": 1.0,
      "release_badge": ""
    },
    {
      "id": "316e51e37de1",
      "pillar": "anime",
      "title": "SHIBOYUGI: Playing Death Games to Put Food on the Table 44: Cloudy Beach Anime Film Reveals New Visual, Trailer",
      "source": "AnimeNewsNetwork",
      "source_url": "https://www.animenewsnetwork.com/news/2026-05-17/shiboyugi-playing-death-games-to-put-food-on-the-table-44-cloudy-beach-anime-film-reveals-new-/.237451",
      "thumbnail": "/drops/thumbs/316e51e37de1.jpg",
      "published": "",
      "relative_time": "today",
      "score": 1.0,
      "release_badge": ""
    },
    {
      "id": "c82c86bb7001",
      "pillar": "gaming",
      "title": "Rumor: GTA 6’s 3rd Trailer Will Come Out Before Pre-Orders Begin, With 6 Editions Available",
      "source": "Gameranx",
      "source_url": "https://gameranx.com/updates/id/562698/article/rumor-gta-6s-3rd-trailer-will-come-out-before-pre-orders-begin-with-6-editions-available/",
      "thumbnail": "/drops/thumbs/c82c86bb7001.jpg",
      "published": "",
      "relative_time": "today",
      "score": 1.0,
      "release_badge": ""
    },
    {
      "id": "20e4abeaa097",
      "pillar": "gaming",
      "title": "Overwatch Is Officially Answering The Call In Fortnite",
      "source": "Gameranx",
      "source_url": "https://gameranx.com/updates/id/562691/article/overwatch-is-officially-answering-the-call-in-fortnite/",
      "thumbnail": "/drops/thumbs/20e4abeaa097.jpg",
      "published": "",
      "relative_time": "today",
      "score": 1.0,
      "release_badge": ""
    },
    {
      "id": "a3878d871747",
      "pillar": "gaming",
      "title": "Feature 15 Years Ago Today, We All Pushed Square to Doubt",
      "source": "PushSquare",
      "source_url": "https://www.pushsquare.com/features/15-years-ago-today-we-all-pushed-square-to-doubt",
      "thumbnail": "/drops/thumbs/a3878d871747.jpg",
      "published": "",
      "relative_time": "today",
      "score": 1.0,
      "release_badge": ""
    },
    {
      "id": "9cb5e266f108",
      "pillar": "gaming",
      "title": "Subnautica 2 lays strong foundations for an improved sequel, but the depths of early access remain murky",
      "source": "GamesRadar",
      "source_url": "https://www.gamesradar.com/games/survival/subnautica-2-lays-strong-foundations-for-an-improved-sequel-but-the-depths-of-early-access-remain-murky/",
      "thumbnail": "/drops/thumbs/9cb5e266f108.jpg",
      "published": "",
      "relative_time": "today",
      "score": 1.0,
      "release_badge": ""
    },
    {
      "id": "28bf02185073",
      "pillar": "gaming",
      "title": "Stores At A Loss For Words After Being Sent Sealed Copies Of Rare PS4 Game Poop Slinger",
      "source": "Kotaku",
      "source_url": "https://kotaku.com/stores-at-a-loss-for-words-after-being-sent-sealed-copies-of-rare-ps4-game-poop-slinger-2000696767",
      "thumbnail": "/drops/thumbs/28bf02185073.jpg",
      "published": "",
      "relative_time": "today",
      "score": 1.0,
      "release_badge": ""
    },
    {
      "id": "c7e2f74c326e",
      "pillar": "gaming",
      "title": "Poll Would You Buy an inFAMOUS Collection for PS5?",
      "source": "PushSquare",
      "source_url": "https://www.pushsquare.com/news/2026/05/poll-would-you-buy-an-infamous-collection-for-ps5",
      "thumbnail": "/drops/thumbs/c7e2f74c326e.jpg",
      "published": "",
      "relative_time": "today",
      "score": 1.0,
      "release_badge": ""
    },
    {
      "id": "54b419ee6081",
      "pillar": "gaming",
      "title": "Forza Horizon 6 immediately beats its predecessor's all-time Steam record with over 130,000 concurrent players",
      "source": "GamesRadar",
      "source_url": "https://www.gamesradar.com/games/racing/forza-horizon-6-immediately-beats-its-predecessors-all-time-steam-record-with-130-000-concurrent-players-and-thats-only-counting-people-willing-to-pay-usd120-for-early-access/",
      "thumbnail": "/drops/thumbs/54b419ee6081.jpg",
      "published": "",
      "relative_time": "today",
      "score": 1.0,
      "release_badge": ""
    },
    {
      "id": "ab34721d4d63",
      "pillar": "gaming",
      "title": "Prolific Repacker Of Pirated Games Announces They’re Stepping Back To Focus On Law Degree",
      "source": "Kotaku",
      "source_url": "https://kotaku.com/prolific-repacker-of-pirated-games-announces-theyre-stepping-back-to-focus-on-law-degree-2000696765",
      "thumbnail": "/drops/thumbs/ab34721d4d63.jpg",
      "published": "",
      "relative_time": "today",
      "score": 1.0,
      "release_badge": ""
    }
  ],
  "homepage": [
    "5d4bbf488e7f",
    "fbcaff4991e8",
    "43151d13faa3",
    "254a561ec862",
    "37fc53e0f8e7",
    "c82c86bb7001"
  ]
}