{
  "schema": 2,
  "generated_utc": "2026-06-15T15:35:08+00:00",
  "items": [
    {
      "id": "094b1500b6a8",
      "pillar": "sneakers",
      "title": "Air Jordan 3 “BIN 23” (IO7744-600): 2026 Release Date & Info",
      "source": "NiceKicks",
      "source_url": "https://www.nicekicks.com/air-jordan-3-bin-23-io7744-600-drop/",
      "thumbnail": "/drops/thumbs/094b1500b6a8.jpg",
      "published": "2026-06-12T10:51:24",
      "relative_time": "today",
      "score": 5.0,
      "release_badge": "🔥 Banger"
    },
    {
      "id": "15fa64d17ff5",
      "pillar": "sneakers",
      "title": "Air Jordan 1 Low Joins The “Bloodline” Family",
      "source": "SneakerBarDetroit",
      "source_url": "https://sneakerbardetroit.com/air-jordan-1-low-bloodline-553558-076/",
      "thumbnail": "/drops/thumbs/15fa64d17ff5.jpg",
      "published": "",
      "relative_time": "today",
      "score": 5.0,
      "release_badge": "🔥 Banger"
    },
    {
      "id": "779db71fc001",
      "pillar": "sneakers",
      "title": "Air Jordan 5 “Black Carolina” (DD0587-008) June 2026 Release Date & Info",
      "source": "NiceKicks",
      "source_url": "https://www.nicekicks.com/air-jordan-5-black-carolina-dd0587-008-drop/",
      "thumbnail": "/drops/thumbs/779db71fc001.jpg",
      "published": "2026-06-15T07:31:40",
      "relative_time": "today",
      "score": 3.0,
      "release_badge": "Drops This Month"
    },
    {
      "id": "8362d1bf79ba",
      "pillar": "sneakers",
      "title": "Air Jordan 5 “Black University Blue” Returns June 2026",
      "source": "Sneakerfiles",
      "source_url": "https://www.sneakerfiles.com/air-jordan-5-black-university-blue-2026/",
      "thumbnail": "/drops/thumbs/8362d1bf79ba.jpg",
      "published": "2026-06-06T22:42:50",
      "relative_time": "today",
      "score": 3.0,
      "release_badge": "Drops This Month"
    },
    {
      "id": "a3e23bbf57cc",
      "pillar": "sneakers",
      "title": "Air Jordan 1 Low OG “Pine Green” June 2026 Release Date & Info",
      "source": "NiceKicks",
      "source_url": "https://www.nicekicks.com/air-jordan-1-low-og-pine-green-ir2283-030/",
      "thumbnail": "/drops/thumbs/a3e23bbf57cc.jpg",
      "published": "2026-06-05T17:50:18",
      "relative_time": "today",
      "score": 3.0,
      "release_badge": "Drops This Month"
    },
    {
      "id": "aa087d5a1590",
      "pillar": "sneakers",
      "title": "Air Jordan 7 “Miro” (IQ6573-100) July 2026 Release Date & Info",
      "source": "NiceKicks",
      "source_url": "https://www.nicekicks.com/air-jordan-7-miro-iq6573-100-2026-drop/",
      "thumbnail": "/drops/thumbs/aa087d5a1590.jpg",
      "published": "2026-06-15T08:08:53",
      "relative_time": "today",
      "score": 2.4,
      "release_badge": "Drops Next Month"
    },
    {
      "id": "6f835bbe3ddc",
      "pillar": "sneakers",
      "title": "Air Jordan 3 OG “True Blue” Returns July 2026",
      "source": "Sneakerfiles",
      "source_url": "https://www.sneakerfiles.com/air-jordan-3-true-blue-2026/",
      "thumbnail": "/drops/thumbs/6f835bbe3ddc.jpg",
      "published": "2026-06-10T12:36:33",
      "relative_time": "today",
      "score": 2.4,
      "release_badge": "Drops Next Month"
    },
    {
      "id": "993ac8a3c27d",
      "pillar": "sneakers",
      "title": "J Balvin Officially Reveals his Air Jordan 4 “Lemonade” During World Cup Ceremonies",
      "source": "JustFreshKicks",
      "source_url": "https://justfreshkicks.com/j-balvin-air-jordan-4-lemonade-iw2872-700/",
      "thumbnail": "/drops/thumbs/993ac8a3c27d.webp",
      "published": "2026-06-11T17:42:21",
      "relative_time": "today",
      "score": 2.0,
      "release_badge": ""
    },
    {
      "id": "b22cda778a39",
      "pillar": "anime",
      "title": "Move Over Goku and Vegeta, Beerus Has Already Chosen His True Heir",
      "source": "ScreenRant/Anime",
      "source_url": "https://screenrant.com/dragon-ball-beerus-successor-broly-not-vegeta-goku/",
      "thumbnail": "/drops/thumbs/b22cda778a39.png",
      "published": "",
      "relative_time": "today",
      "score": 1.0,
      "release_badge": ""
    },
    {
      "id": "dc28707f9f9d",
      "pillar": "anime",
      "title": "Demon Slayer Infinity Castle Part 2 Is Finally Going To Give Fans The One Villain Death They've Waited 4 Years For",
      "source": "ScreenRant/Anime",
      "source_url": "https://screenrant.com/demon-slayer-infinity-castle-part-2-doma-death/",
      "thumbnail": "/drops/thumbs/dc28707f9f9d.png",
      "published": "",
      "relative_time": "today",
      "score": 1.0,
      "release_badge": ""
    },
    {
      "id": "765f606a55e1",
      "pillar": "anime",
      "title": "11 anime to watch if you like Frieren",
      "source": "Polygon/Anime",
      "source_url": "https://www.polygon.com/best-anime-like-frieren/",
      "thumbnail": "/drops/thumbs/765f606a55e1.jpg",
      "published": "",
      "relative_time": "today",
      "score": 1.0,
      "release_badge": ""
    },
    {
      "id": "d512010facab",
      "pillar": "anime",
      "title": "School of Horns' Mito Aoi Launches New Manga",
      "source": "AnimeNewsNetwork",
      "source_url": "https://www.animenewsnetwork.com/news/2026-06-15/school-of-horns-mito-aoi-launches-new-manga/.238512",
      "thumbnail": "/drops/thumbs/d512010facab.jpg",
      "published": "",
      "relative_time": "today",
      "score": 1.0,
      "release_badge": ""
    },
    {
      "id": "f214c834fdf8",
      "pillar": "anime",
      "title": "Ameku M.D.'s Mikito Chinen Launches New Manga",
      "source": "AnimeNewsNetwork",
      "source_url": "https://www.animenewsnetwork.com/news/2026-06-15/ameku-m.d.s-mikito-chinen-launches-new-manga/.238504",
      "thumbnail": "/drops/thumbs/f214c834fdf8.jpg",
      "published": "",
      "relative_time": "today",
      "score": 1.0,
      "release_badge": ""
    },
    {
      "id": "d9ec91b643d5",
      "pillar": "anime",
      "title": "Nearly 40 years after its release, Ghost in the Shell is going back to its roots",
      "source": "Polygon/Anime",
      "source_url": "https://www.polygon.com/ghost-in-the-shell-remake-manga-relationship/",
      "thumbnail": "/drops/thumbs/d9ec91b643d5.jpg",
      "published": "",
      "relative_time": "today",
      "score": 1.0,
      "release_badge": ""
    },
    {
      "id": "f00a120ee6cc",
      "pillar": "anime",
      "title": "Jun Nishikawa's Maken no Deshi wa Munō de Saikyō! Manga Adaptation Ends",
      "source": "AnimeNewsNetwork",
      "source_url": "https://www.animenewsnetwork.com/news/2026-06-15/jun-nishikawa-maken-no-deshi-wa-muno-de-saikyo-manga-adaptation-ends/.238507",
      "thumbnail": "/drops/thumbs/f00a120ee6cc.jpg",
      "published": "",
      "relative_time": "today",
      "score": 1.0,
      "release_badge": ""
    },
    {
      "id": "042e885e39fe",
      "pillar": "anime",
      "title": "Netflix's Hottest Action Thriller Of The Month Is Officially Out, And It Blasts A Broken System",
      "source": "ScreenRant/Anime",
      "source_url": "https://screenrant.com/netflix-action-thriller-teach-you-a-lesson-broken-system/",
      "thumbnail": "/drops/thumbs/042e885e39fe.png",
      "published": "",
      "relative_time": "today",
      "score": 1.0,
      "release_badge": ""
    },
    {
      "id": "e8515f1015b8",
      "pillar": "gaming",
      "title": "News Sony 'Hopes' to Launch PS5's God of War Laufey in the First Half of 2027",
      "source": "PushSquare",
      "source_url": "https://www.pushsquare.com/news/2026/06/sony-hopes-to-launch-ps5s-god-of-war-laufey-in-the-first-half-of-2027",
      "thumbnail": "/drops/thumbs/e8515f1015b8.jpg",
      "published": "",
      "relative_time": "today",
      "score": 1.0,
      "release_badge": ""
    },
    {
      "id": "53d668079e16",
      "pillar": "gaming",
      "title": "Final Fantasy 7 Revelation lead thinks a potential Final Fantasy 6 remake would \"be in better hands\" with another dev",
      "source": "GamesRadar",
      "source_url": "https://www.gamesradar.com/games/final-fantasy/final-fantasy-7-revelation-lead-thinks-a-potential-final-fantasy-6-remake-would-be-in-better-hands-if-it-went-to-another-creator-in-square-enix/",
      "thumbnail": "/drops/thumbs/53d668079e16.jpg",
      "published": "",
      "relative_time": "today",
      "score": 1.0,
      "release_badge": ""
    },
    {
      "id": "6d5094e7044d",
      "pillar": "gaming",
      "title": "Rumor: Clair Obscur: Expedition 33 Coming To Switch 2 This Year",
      "source": "Gameranx",
      "source_url": "https://gameranx.com/updates/id/563063/article/rumor-clair-obscur-expedition-33-coming-to-switch-2-this-year/",
      "thumbnail": "/drops/thumbs/6d5094e7044d.jpg",
      "published": "",
      "relative_time": "today",
      "score": 1.0,
      "release_badge": ""
    },
    {
      "id": "510701dc8149",
      "pillar": "gaming",
      "title": "Trump Uses Persona 5 , A Game About Fighting Corrupt Politicians And Sex Offenders, To Spread Propaganda",
      "source": "Kotaku",
      "source_url": "https://kotaku.com/donald-trump-white-house-meme-persona-5-all-out-attack-2000706632",
      "thumbnail": "/drops/thumbs/510701dc8149.jpg",
      "published": "",
      "relative_time": "today",
      "score": 1.0,
      "release_badge": ""
    },
    {
      "id": "a9446293dd50",
      "pillar": "gaming",
      "title": "News Final Fantasy 7 Remake and Rebirth Sales Seemingly Spike After Revelation Reveal",
      "source": "PushSquare",
      "source_url": "https://www.pushsquare.com/news/2026/06/final-fantasy-7-remake-and-rebirth-sales-seemingly-spike-after-revelation-reveal",
      "thumbnail": "/drops/thumbs/a9446293dd50.jpg",
      "published": "",
      "relative_time": "today",
      "score": 1.0,
      "release_badge": ""
    },
    {
      "id": "26e8dfd03cb9",
      "pillar": "gaming",
      "title": "Rumor: Marathon Sponsor Deal Asks Streamers Not To Talk About Destiny 3",
      "source": "Gameranx",
      "source_url": "https://gameranx.com/updates/id/563061/article/rumor-marathon-sponsor-deal-asks-streamers-not-to-talk-about-destiny-3/",
      "thumbnail": "/drops/thumbs/26e8dfd03cb9.jpg",
      "published": "",
      "relative_time": "today",
      "score": 1.0,
      "release_badge": ""
    },
    {
      "id": "a574706302af",
      "pillar": "gaming",
      "title": "GTA 5 and Red Dead Redemption 2 lead says \"the most fun thing\" in any Rockstar game is \"the systems that we make\"",
      "source": "GamesRadar",
      "source_url": "https://www.gamesradar.com/games/grand-theft-auto/gta-5-and-red-dead-redemption-2-writer-dan-houser-says-the-most-fun-thing-about-the-game-isnt-any-rubbish-we-write-its-the-systems-that-we-make/",
      "thumbnail": "/drops/thumbs/a574706302af.jpg",
      "published": "",
      "relative_time": "today",
      "score": 1.0,
      "release_badge": ""
    },
    {
      "id": "36b85c070cfd",
      "pillar": "gaming",
      "title": "Fans Find Hidden Info On Zelda: Ocarina Of Time Remake, Nintendo Promptly Deletes It",
      "source": "Kotaku",
      "source_url": "https://kotaku.com/hidden-info-zelda-ocarina-of-time-remake-nintendo-deleted-store-html-info-switch-2-2000706626",
      "thumbnail": "/drops/thumbs/36b85c070cfd.jpg",
      "published": "",
      "relative_time": "today",
      "score": 1.0,
      "release_badge": ""
    }
  ],
  "homepage": [
    "094b1500b6a8",
    "15fa64d17ff5",
    "779db71fc001",
    "b22cda778a39",
    "8362d1bf79ba",
    "e8515f1015b8"
  ]
}