{
  "schema": 2,
  "generated_utc": "2026-05-19T03:33:14+00:00",
  "items": [
    {
      "id": "1f8cbf1d8983",
      "pillar": "sneakers",
      "title": "Air Jordan 12 “Bloodline” (CT8013-003) May 2026 Release Date & Info",
      "source": "NiceKicks",
      "source_url": "https://www.nicekicks.com/air-jordan-12-bloodline-ct8013-003-drop/",
      "thumbnail": "/drops/thumbs/1f8cbf1d8983.jpg",
      "published": "2026-05-16T17:42:00",
      "relative_time": "today",
      "score": 7.5,
      "release_badge": "🔥 Banger"
    },
    {
      "id": "5d4bbf488e7f",
      "pillar": "sneakers",
      "title": "Nigel Sylvester x Air Jordan 4 “Brick After Brick” May Release Date & Info",
      "source": "NiceKicks",
      "source_url": "https://www.nicekicks.com/nigel-sylvester-air-jordan-4-brick-after-brick-iq8055-100-drop/",
      "thumbnail": "/drops/thumbs/5d4bbf488e7f.jpg",
      "published": "2026-05-16T07:21:30",
      "relative_time": "today",
      "score": 7.5,
      "release_badge": "🔥 Banger"
    },
    {
      "id": "43151d13faa3",
      "pillar": "sneakers",
      "title": "RUMORED: Air Jordan 8 PRM “BIN 23” Set for Summer 2026 Release",
      "source": "NiceKicks",
      "source_url": "https://www.nicekicks.com/air-jordan-8-prm-bin-23-io2053-300-drop/",
      "thumbnail": "/drops/thumbs/43151d13faa3.png",
      "published": "2026-05-12T11:21:07",
      "relative_time": "today",
      "score": 5.0,
      "release_badge": "🔥 Banger"
    },
    {
      "id": "37fc53e0f8e7",
      "pillar": "sneakers",
      "title": "The Air Jordan 3 “World’s Best Dad” Releases Tomorrow",
      "source": "JustFreshKicks",
      "source_url": "https://justfreshkicks.com/air-jordan-3-worlds-best-dad-if4396-103/",
      "thumbnail": "/drops/thumbs/37fc53e0f8e7.jpg",
      "published": "2026-05-15T04:32:00",
      "relative_time": "today",
      "score": 3.0,
      "release_badge": "Drops This Week"
    },
    {
      "id": "7d4dc371b041",
      "pillar": "sneakers",
      "title": "Air Jordan 1 High OG “Shop Jacket” (Workwear) Releases May 2026",
      "source": "Sneakerfiles",
      "source_url": "https://www.sneakerfiles.com/air-jordan-1-high-og-workwear/",
      "thumbnail": "/drops/thumbs/7d4dc371b041.jpg",
      "published": "2026-05-15T00:28:37",
      "relative_time": "today",
      "score": 3.0,
      "release_badge": "Drops This Month"
    },
    {
      "id": "b7892b717b41",
      "pillar": "sneakers",
      "title": "Air Jordan 4 “Toro Bravo” 2026 May Release Date & Info",
      "source": "NiceKicks",
      "source_url": "https://www.nicekicks.com/air-jordan-4-toro-bravo-fq8138-600-drop/",
      "thumbnail": "/drops/thumbs/b7892b717b41.jpg",
      "published": "2026-05-12T12:28:47",
      "relative_time": "today",
      "score": 3.0,
      "release_badge": "Drops This Month"
    },
    {
      "id": "dd5fb84e4443",
      "pillar": "sneakers",
      "title": "Air Jordan 3 “Brazil” Releases May 16th",
      "source": "SneakerBarDetroit",
      "source_url": "https://sneakerbardetroit.com/air-jordan-3-brazil-iv4871-400-release-date/",
      "thumbnail": "/drops/thumbs/dd5fb84e4443.webp",
      "published": "",
      "relative_time": "today",
      "score": 3.0,
      "release_badge": "Drops This Month"
    },
    {
      "id": "b2201e525307",
      "pillar": "sneakers",
      "title": "Air Jordan 3 “Utility” Releases Spring 2027",
      "source": "Sneakerfiles",
      "source_url": "https://www.sneakerfiles.com/air-jordan-3-utility-black-fire-red/",
      "thumbnail": "/drops/thumbs/b2201e525307.jpg",
      "published": "2026-05-18T15:32:31",
      "relative_time": "today",
      "score": 2.0,
      "release_badge": ""
    },
    {
      "id": "d7839edf4137",
      "pillar": "hiphop",
      "title": "Donald Trump’s Adviser Denies Nicki Minaj Seeking Favors From The Administration",
      "source": "AllHipHop",
      "source_url": "https://allhiphop.com/news/donald-trumps-adviser-denies-nicki-minaj-seeking-favors-from-the-administration/",
      "thumbnail": "/drops/thumbs/d7839edf4137.jpg",
      "published": "2026-05-18T23:00:00",
      "relative_time": "today",
      "score": 1.0,
      "release_badge": ""
    },
    {
      "id": "b9296595297d",
      "pillar": "hiphop",
      "title": "Alabama Rapper Admits To Killing His Ex On Facebook, Then Himself In Graveyard",
      "source": "AllHipHop",
      "source_url": "https://allhiphop.com/news/alabama-rapper-admits-to-killing-his-wife-on-facebook-then-himself-in-graveyard/",
      "thumbnail": "/drops/thumbs/b9296595297d.jpg",
      "published": "2026-05-18T22:00:00",
      "relative_time": "today",
      "score": 1.0,
      "release_badge": ""
    },
    {
      "id": "105704e4e22b",
      "pillar": "hiphop",
      "title": "Max B Says He’s Better Than Big Daddy Kane, Internet Goes Off",
      "source": "AllHipHop",
      "source_url": "https://allhiphop.com/rumors/max-b-says-hes-better-than-big-daddy-kane-internet-goes-off/",
      "thumbnail": "/drops/thumbs/105704e4e22b.jpg",
      "published": "2026-05-18T20:36:39",
      "relative_time": "today",
      "score": 1.0,
      "release_badge": ""
    },
    {
      "id": "495ade97a45b",
      "pillar": "hiphop",
      "title": "Family Life in Phoenix: Activities, Events, and Things to Do with Kids",
      "source": "AllHipHop",
      "source_url": "https://allhiphop.com/uncategorized/family-life-in-phoenix-activities-events-and-things-to-do-with-kids/",
      "thumbnail": "/drops/thumbs/495ade97a45b.jpg",
      "published": "2026-05-18T20:19:15",
      "relative_time": "today",
      "score": 1.0,
      "release_badge": ""
    },
    {
      "id": "1e4b53058ee3",
      "pillar": "hiphop",
      "title": "How Senior Home Caregivers Help With Hygiene and Medication Reminders",
      "source": "AllHipHop",
      "source_url": "https://allhiphop.com/uncategorized/how-senior-home-caregivers-help-with-hygiene-and-medication-reminders/",
      "thumbnail": "/drops/thumbs/1e4b53058ee3.png",
      "published": "2026-05-18T20:12:48",
      "relative_time": "today",
      "score": 1.0,
      "release_badge": ""
    },
    {
      "id": "918eb2c5ceb8",
      "pillar": "hiphop",
      "title": "Donald Trump Posts Shocking Image Of Himself Escorting An Alien In Chains",
      "source": "AllHipHop",
      "source_url": "https://allhiphop.com/news/donald-trump-posts-shocking-image-of-himself-escorting-an-alien-in-chains/",
      "thumbnail": "/drops/thumbs/918eb2c5ceb8.jpg",
      "published": "2026-05-18T20:00:00",
      "relative_time": "today",
      "score": 1.0,
      "release_badge": ""
    },
    {
      "id": "4a6ae789260d",
      "pillar": "hiphop",
      "title": "Infamous Racist OJ Simpson Cop Mark Fuhrman Dead, Rappers Like Eminem & The Lox Kept His Name Alive",
      "source": "AllHipHop",
      "source_url": "https://allhiphop.com/news/infamous-racist-oj-simpson-cop-mark-fuhrman-dead/",
      "thumbnail": "/drops/thumbs/4a6ae789260d.jpg",
      "published": "2026-05-18T19:21:54",
      "relative_time": "today",
      "score": 1.0,
      "release_badge": ""
    },
    {
      "id": "7e5800e50042",
      "pillar": "hiphop",
      "title": "6ix9ine Turns Into Preacher; Says Jesus Is Coming Back Soon, Says He Is Meant To Save People",
      "source": "AllHipHop",
      "source_url": "https://allhiphop.com/news/6ix9ine-turns-into-preacher-says-jesus-is-coming-back-soon-says-he-is-meant-to-save-people/",
      "thumbnail": "/drops/thumbs/7e5800e50042.jpg",
      "published": "2026-05-18T18:00:00",
      "relative_time": "today",
      "score": 1.0,
      "release_badge": ""
    },
    {
      "id": "710cdc0db682",
      "pillar": "anime",
      "title": "10 years ago, Mob Psycho 100 proved itself to be a cut above most shonen anime",
      "source": "Polygon/Anime",
      "source_url": "https://www.polygon.com/mob-psycho-100-ten-year-anniversary/",
      "thumbnail": "/drops/thumbs/710cdc0db682.png",
      "published": "",
      "relative_time": "today",
      "score": 1.0,
      "release_badge": ""
    },
    {
      "id": "aa945552abe7",
      "pillar": "anime",
      "title": "One Piece Finally Delivered The Moment Fans Have Waited 20 Years For, And It Didn't Disappoint",
      "source": "ScreenRant/Anime",
      "source_url": "https://screenrant.com/one-piece-elbaph-payoff-20-years/",
      "thumbnail": "/drops/thumbs/aa945552abe7.jpg",
      "published": "",
      "relative_time": "today",
      "score": 1.0,
      "release_badge": ""
    },
    {
      "id": "14e0dfad4539",
      "pillar": "anime",
      "title": "Tubi TV Licenses Yokoso Scooby-Doo! Anime by OLM",
      "source": "AnimeNewsNetwork",
      "source_url": "https://www.animenewsnetwork.com/news/2026-05-18/tubi-tv-licenses-yokoso-scooby-doo-anime-by-olm/.237510",
      "thumbnail": "/drops/thumbs/14e0dfad4539.jpg",
      "published": "",
      "relative_time": "today",
      "score": 1.0,
      "release_badge": ""
    },
    {
      "id": "fd3a5844e600",
      "pillar": "anime",
      "title": "'You, Fireworks, and Our Promise' Anime Film's Trailer Unveils More Cast & Staff, Theme Song",
      "source": "AnimeNewsNetwork",
      "source_url": "https://www.animenewsnetwork.com/news/2026-05-18/you-fireworks-and-our-promise-anime-film-trailer-unveils-more-cast-and-staff-theme-song/.237508",
      "thumbnail": "/drops/thumbs/fd3a5844e600.jpg",
      "published": "",
      "relative_time": "today",
      "score": 1.0,
      "release_badge": ""
    },
    {
      "id": "31d54ee0fe5c",
      "pillar": "anime",
      "title": "Witch Hat Atelier fixes the biggest problem with magic-focused anime",
      "source": "Polygon/Anime",
      "source_url": "https://www.polygon.com/witch-hat-atelier-crunchyroll-popular-anime/",
      "thumbnail": "/drops/thumbs/31d54ee0fe5c.jpg",
      "published": "",
      "relative_time": "today",
      "score": 1.0,
      "release_badge": ""
    },
    {
      "id": "d084fdbb62e7",
      "pillar": "anime",
      "title": "Netflix's New Superhero Series Is The Perfect Successor To An Iconic 2017 Classic",
      "source": "ScreenRant/Anime",
      "source_url": "https://screenrant.com/netflix-wonderfools-strong-girl-bong-soon-superhero-successor/",
      "thumbnail": "/drops/thumbs/d084fdbb62e7.png",
      "published": "",
      "relative_time": "today",
      "score": 1.0,
      "release_badge": ""
    },
    {
      "id": "8b56733d33ae",
      "pillar": "anime",
      "title": "Manga Mavericks Licenses 'Tie Me Up, Stare Me Down' Manga",
      "source": "AnimeNewsNetwork",
      "source_url": "https://www.animenewsnetwork.com/news/2026-05-18/manga-mavericks-licenses-tie-me-up-stare-me-down-manga/.237500",
      "thumbnail": "/drops/thumbs/8b56733d33ae.jpg",
      "published": "",
      "relative_time": "today",
      "score": 1.0,
      "release_badge": ""
    },
    {
      "id": "1dde01591de8",
      "pillar": "anime",
      "title": "Trigun Stargaze's Milly Is 2026's Undisputed Queen Of Crunchyroll Anime (Exclusive)",
      "source": "ScreenRant/Anime",
      "source_url": "https://screenrant.com/trigun-stargaze-milly-thompson-queen-2026-anime/",
      "thumbnail": "/drops/thumbs/1dde01591de8.jpg",
      "published": "",
      "relative_time": "today",
      "score": 1.0,
      "release_badge": ""
    },
    {
      "id": "0bf595ed7c6d",
      "pillar": "gaming",
      "title": "GTA 6 pre-order rumors live: we're debunking speculation, verifying listings, and watching prices as they happen",
      "source": "GamesRadar",
      "source_url": "https://www.gamesradar.com/live/news/gta-6-pre-orders-live-updates-may/",
      "thumbnail": "/drops/thumbs/0bf595ed7c6d.jpg",
      "published": "",
      "relative_time": "today",
      "score": 1.0,
      "release_badge": ""
    },
    {
      "id": "b1caddc0af78",
      "pillar": "gaming",
      "title": "Rumor Debunked? GTA 6 Community Believes Best Buy Got The Pre-Order Date Wrong",
      "source": "Gameranx",
      "source_url": "https://gameranx.com/updates/id/562722/article/rumor-debunked-gta-6-community-believes-best-buy-got-the-pre-order-date-wrong/",
      "thumbnail": "/drops/thumbs/b1caddc0af78.jpg",
      "published": "",
      "relative_time": "today",
      "score": 1.0,
      "release_badge": ""
    },
    {
      "id": "3d637f3432cd",
      "pillar": "gaming",
      "title": "Rumor: Rockstar Will Make Reviewers Play GTA 6 In A Closed Door Location",
      "source": "Gameranx",
      "source_url": "https://gameranx.com/updates/id/562717/article/rumor-rockstar-will-make-reviewers-play-gta-6-in-a-closed-door-location/",
      "thumbnail": "/drops/thumbs/3d637f3432cd.jpg",
      "published": "",
      "relative_time": "today",
      "score": 1.0,
      "release_badge": ""
    },
    {
      "id": "9313ad1fdfcf",
      "pillar": "gaming",
      "title": "Take-Two CEO Confirms GTA 6 Should Have Released Last May 2025, Restates It’s Coming This November",
      "source": "Gameranx",
      "source_url": "https://gameranx.com/updates/id/562712/article/take-two-ceo-confirms-gta-6-should-have-released-last-may-2025-restates-its-coming-this-november/",
      "thumbnail": "/drops/thumbs/9313ad1fdfcf.png",
      "published": "",
      "relative_time": "today",
      "score": 1.0,
      "release_badge": ""
    },
    {
      "id": "fc2b8d2c05d2",
      "pillar": "gaming",
      "title": "News PS5 Fans Vote Jak & Daxter As Their Most Wanted PlayStation Revival",
      "source": "PushSquare",
      "source_url": "https://www.pushsquare.com/news/2026/05/ps5-fans-vote-jak-and-daxter-as-their-most-wanted-playstation-revival",
      "thumbnail": "/drops/thumbs/fc2b8d2c05d2.jpg",
      "published": "",
      "relative_time": "today",
      "score": 1.0,
      "release_badge": ""
    },
    {
      "id": "45eed0a1e375",
      "pillar": "gaming",
      "title": "News 'Pretty Awesome, Huh?': Even the Father of Final Fantasy Can't Avoid AI Drama",
      "source": "PushSquare",
      "source_url": "https://www.pushsquare.com/news/2026/05/pretty-awesome-huh-even-the-father-of-final-fantasy-cant-avoid-ai-drama",
      "thumbnail": "/drops/thumbs/45eed0a1e375.jpg",
      "published": "",
      "relative_time": "today",
      "score": 1.0,
      "release_badge": ""
    },
    {
      "id": "241f701fb1bf",
      "pillar": "gaming",
      "title": "Ex-Google CEO Can Barely Get A Word Out About AI As He’s Booed And Heckled",
      "source": "Kotaku",
      "source_url": "https://kotaku.com/eric-schmidt-ai-graduation-speech-university-arizona-2000697034",
      "thumbnail": "/drops/thumbs/241f701fb1bf.jpg",
      "published": "",
      "relative_time": "today",
      "score": 1.0,
      "release_badge": ""
    },
    {
      "id": "79dbff3bb659",
      "pillar": "gaming",
      "title": "Big Preview Assassin's Creed Black Flag Resynced: The Big Preview",
      "source": "GamesRadar",
      "source_url": "https://www.gamesradar.com/games/assassin-s-creed/assassins-creed-black-flag-resynced-the-big-preview-hub/",
      "thumbnail": "/drops/thumbs/79dbff3bb659.jpg",
      "published": "",
      "relative_time": "today",
      "score": 1.0,
      "release_badge": ""
    }
  ],
  "homepage": [
    "1f8cbf1d8983",
    "d7839edf4137",
    "5d4bbf488e7f",
    "710cdc0db682",
    "43151d13faa3",
    "0bf595ed7c6d"
  ]
}