{
  "schema": 2,
  "generated_utc": "2026-05-30T16:20:44+00:00",
  "source": "drops_feed_direct_scrape",
  "items": [
    {
      "title": "Travis Scott x Air Jordan 1 Low OG SP “Tropical Pink” (IQ7604-101) May Release Date & Info",
      "url": "https://www.nicekicks.com/travis-scott-air-jordan-1-low-og-sp-tropical-pink-iq7604-101-drop/",
      "pillar": "sneakers",
      "score": 3.0,
      "article_slug": null
    },
    {
      "title": "Travis Scott x Air Jordan 1 Low OG SP “Shy Pink” (IQ7604-100) May Release Date & Info",
      "url": "https://www.nicekicks.com/travis-scott-air-jordan-1-low-og-sp-shy-pink-iq7604-100-drop/",
      "pillar": "sneakers",
      "score": 3.0,
      "article_slug": null
    },
    {
      "title": "The 2026 Air Jordan 4 Retro “Toro Bravo” Releases Tomorrow",
      "url": "https://justfreshkicks.com/air-jordan-4-toro-bravo-fq8138-600/",
      "pillar": "sneakers",
      "score": 3.0,
      "article_slug": null
    },
    {
      "title": "Travis Scott x Air Jordan 1 Low “Pink Pack” Releases May 29th",
      "url": "https://sneakerbardetroit.com/travis-scott-air-jordan-1-low-pink-pack/",
      "pillar": "sneakers",
      "score": 3.0,
      "article_slug": null
    },
    {
      "title": "Air Jordan 1 Low OG “Phantom Pine Green” Releases June 2026",
      "url": "https://www.sneakerfiles.com/air-jordan-1-low-og-phantom-pine-green/",
      "pillar": "sneakers",
      "score": 2.4,
      "article_slug": null
    },
    {
      "title": "Air Jordan 1 Low OG “Sail” Release Date & Info",
      "url": "https://www.nicekicks.com/air-jordan-1-low-og-sail-hq6998-100/",
      "pillar": "sneakers",
      "score": 2.0,
      "article_slug": null
    },
    {
      "title": "Air Jordan 14 Low “Valentines Day” Releases February 2027",
      "url": "https://www.sneakerfiles.com/air-jordan-14-low-valentines-day-2027/",
      "pillar": "sneakers",
      "score": 2.0,
      "article_slug": null
    },
    {
      "title": "Air Jordan 8 “Knicks” Releases December 2026",
      "url": "https://www.sneakerfiles.com/air-jordan-8-knicks-2026/",
      "pillar": "sneakers",
      "score": 2.0,
      "article_slug": null
    },
    {
      "title": "T.I. Recognized For Building Black Wealth Beyond Music",
      "url": "https://allhiphop.com/news/t-i-recognized-for-building-black-wealth-beyond-music/",
      "pillar": "hiphop",
      "score": 1.0,
      "article_slug": null
    },
    {
      "title": "Utah just approved an AI data center bigger than Manhattan. You won’t believe how much water it’ll require: ‘We dont want it!’",
      "url": "https://allhiphop.com/newsbreak/utah-ai-data-center-stratos-water-requirement/",
      "pillar": "hiphop",
      "score": 1.0,
      "article_slug": null
    },
    {
      "title": "Taxstone Hit With Three Extra Years After Prison Contraband Operation Foiled",
      "url": "https://allhiphop.com/news/taxstone-hit-with-three-extra-years-after-prison-contraband-operation-foiled/",
      "pillar": "hiphop",
      "score": 1.0,
      "article_slug": null
    },
    {
      "title": "Missouri woman looks at her aquarium. Then she notices an uninvited mystery hatchling slithering around: ‘I don’t have any fish in here’",
      "url": "https://allhiphop.com/newsbreak/missouri-aquarium-mystery-creature/",
      "pillar": "hiphop",
      "score": 1.0,
      "article_slug": null
    },
    {
      "title": "Lexnour Teases New Single “Baby Don’t Play,” Hinting at a Genre-Blending Sound Fans Haven’t Heard Before",
      "url": "https://allhiphop.com/music/lexnour-teases-new-single-baby-dont-play-hinting-at-a-genre-blending-sound-fans-havent-heard-before/",
      "pillar": "hiphop",
      "score": 1.0,
      "article_slug": null
    },
    {
      "title": "BET Announces Premiere Date for Damon Dash’s ‘OG STORIES’ Docuseries",
      "url": "https://thesource.com/2026/05/30/bet-damon-dash-og-stories-premiere/",
      "pillar": "hiphop",
      "score": 1.0,
      "article_slug": null
    },
    {
      "title": "‘So that was strike one’: Las Vegas woman goes on Hinge date. Then he asks her a question about her ring",
      "url": "https://allhiphop.com/newsbreak/las-vegas-hinge-stack-dating/",
      "pillar": "hiphop",
      "score": 1.0,
      "article_slug": null
    },
    {
      "title": "A$AP Rocky Launches Don’t Be Dumb World Tour with Sold-Out Chicago Show",
      "url": "https://thesource.com/2026/05/30/asap-rocky-dont-be-dumb-tour-chicago/",
      "pillar": "hiphop",
      "score": 1.0,
      "article_slug": null
    },
    {
      "title": "Dragon Ball Is Officially Switching Genres In 2027, And It Will Be Epic",
      "url": "https://screenrant.com/dragon-ball-super-galactic-patrol-change-genre/",
      "pillar": "anime",
      "score": 1.0,
      "article_slug": null
    },
    {
      "title": "New Kaiju No. 8 Anime Short Unveils Story, Staff, Fall Debut",
      "url": "https://www.animenewsnetwork.com/news/2026-05-30/new-kaiju-no-8-anime-short-unveils-story-staff-fall-debut/.237963",
      "pillar": "anime",
      "score": 1.0,
      "article_slug": null
    },
    {
      "title": "Naruto has major new releases set for 2027",
      "url": "https://www.polygon.com/naruto-new-releases-2027/",
      "pillar": "anime",
      "score": 1.0,
      "article_slug": null
    },
    {
      "title": "Ichi the Witch Is Officially Shonen Jump's Next Black Clover-Level Mega Hit",
      "url": "https://screenrant.com/shonen-jump-ichi-the-witch-next-black-clover-hit/",
      "pillar": "anime",
      "score": 1.0,
      "article_slug": null
    },
    {
      "title": "Japanese Animation TV Ranking, May 11-17",
      "url": "https://www.animenewsnetwork.com/news/2026-05-30/japanese-animation-tv-ranking-may-11-17/.237935",
      "pillar": "anime",
      "score": 1.0,
      "article_slug": null
    },
    {
      "title": "One of anime's most celebrated arthouse movies is finally coming to theaters",
      "url": "https://www.polygon.com/one-of-animes-most-celebrated-arthouse-movies-is-finally-coming-to-theaters-27-years-after-it-debuted/",
      "pillar": "anime",
      "score": 1.0,
      "article_slug": null
    },
    {
      "title": "Singer adieu Performs Ascendance of a Bookworm Part 3 Anime's New Ending Song",
      "url": "https://www.animenewsnetwork.com/news/2026-05-30/singer-adieu-performs-ascendance-of-a-bookworm-part-3-anime-new-ending-song/.237968",
      "pillar": "anime",
      "score": 1.0,
      "article_slug": null
    },
    {
      "title": "Every Crunchyroll Anime Awards Anime Of The Year Winner, Ranked From Worst To Best",
      "url": "https://screenrant.com/every-crunchyroll-anime-year-award-winner-ranked-worst-best/",
      "pillar": "anime",
      "score": 1.0,
      "article_slug": null
    },
    {
      "title": "Mina the Hollower forces Devolver Digital to delay Dark Scrolls, which somehow isn't a Soulslike",
      "url": "https://www.gamesradar.com/games/adventure/silksong-and-slay-the-spire-2-well-up-with-pride-as-mina-the-hollower-forces-devolver-digital-to-delay-dark-scrolls-which-somehow-isnt-a-soulslike/",
      "pillar": "gaming",
      "score": 1.0,
      "article_slug": null
    },
    {
      "title": "Rumor: State Of Play’s Big Game Reveal Is Faye’s God Of War Spinoff Game",
      "url": "https://gameranx.com/updates/id/562852/article/rumor-state-of-plays-big-game-reveal-is-fayes-god-of-war-spinoff-game/",
      "pillar": "gaming",
      "score": 1.0,
      "article_slug": null
    },
    {
      "title": "90 % of Call of Duty: Modern Warfare 4’s Reveal Trailer Is “In-Engine” After Activision Pivots To PC First",
      "url": "https://gameranx.com/updates/id/562859/article/90-of-call-of-duty-modern-warfare-4s-reveal-trailer-is-in-engine-after-activision-pivots-to-pc-first/",
      "pillar": "gaming",
      "score": 1.0,
      "article_slug": null
    },
    {
      "title": "Call of Duty: Modern Warfare 4’s Cosmetics And Collabs Will Be “Anchored” To The Narrative",
      "url": "https://gameranx.com/updates/id/562856/article/call-of-duty-modern-warfare-4s-cosmetics-and-collabs-will-be-anchored-to-the-narrative/",
      "pillar": "gaming",
      "score": 1.0,
      "article_slug": null
    },
    {
      "title": "Rumor: Bungie Decided To Drop Destiny 2 At The Start Of 2026 – But They Considered Turning It To ‘Destiny Infinity’",
      "url": "https://gameranx.com/updates/id/562854/article/rumor-bungie-decided-to-drop-destiny-2-at-the-start-of-2026-but-they-considered-turning-it-to-destiny-infinity/",
      "pillar": "gaming",
      "score": 1.0,
      "article_slug": null
    },
    {
      "title": "Call Of Duty: Modern Warfare 4 Officially Revealed – And Confirmed For Nintendo Switch 2",
      "url": "https://gameranx.com/updates/id/562846/article/call-of-duty-modern-warfare-4-officially-revealed-and-confirmed-for-nintendo-switch-2/",
      "pillar": "gaming",
      "score": 1.0,
      "article_slug": null
    },
    {
      "title": "SIGNAL LOST: Call Of Duty 2026 Teasers Triangulate Into A YouTube Livestream In South Korea",
      "url": "https://gameranx.com/updates/id/562839/article/signal-lost-call-of-duty-2026-teasers-triangulate-into-a-youtube-livestream-in-south-korea/",
      "pillar": "gaming",
      "score": 1.0,
      "article_slug": null
    },
    {
      "title": "Poll Are You Happy with Your PS Plus Essential Games for June 2026?",
      "url": "https://www.pushsquare.com/features/poll-are-you-happy-with-your-ps-plus-essential-games-for-june-2026",
      "pillar": "gaming",
      "score": 1.0,
      "article_slug": null
    }
  ]
}